README.rst
setup.py
narcolepsy/__init__.py
narcolepsy/constants.py
narcolepsy/contexts.py
narcolepsy/core.py
narcolepsy/tracers.py
narcolepsy/utils.py
narcolepsy/version.py
narcolepsy.egg-info/PKG-INFO
narcolepsy.egg-info/SOURCES.txt
narcolepsy.egg-info/dependency_links.txt
narcolepsy.egg-info/requires.txt
narcolepsy.egg-info/top_level.txt