Metadata-Version: 1.0
Name: narcolepsy
Version: 0.0.1
Summary: Give your application a break.
Home-page: https://github.com/bworrell
Author: Bryan Worrell
Author-email: bworrell@notmyemail.com
License: UNKNOWN
Keywords: narcolepsy sleep timing useless
Platform: UNKNOWN
